nyc311calendar/__init__.py
nyc311calendar/services.py
nyc311calendar/util.py
nyc311calendar-0.4.1.dist-info/LICENSE
nyc311calendar-0.4.1.dist-info/METADATA
nyc311calendar-0.4.1.dist-info/WHEEL
nyc311calendar-0.4.1.dist-info/top_level.txt
nyc311calendar-0.4.1.dist-info/zip-safe
nyc311calendar-0.4.1.dist-info/RECORD
