Metadata-Version: 2.1
Name: nyc311calendar
Version: 0.4.1
Summary: Simple fetcher for NYC 311 trash collection, school closing, and alternate side parking schedules. Built to drive a Home Assistant add-in.
Home-page: https://github.com/elahd/nyc311calendar
Author: Elahd Bar-Shai
Author-email: nyc311calendar@elahd.com
License: MIT
Project-URL: Bug Tracker, https://github.com/elahd/nyc311calendar/issues
Classifier: Programming Language :: Python :: 3
Classifier: License :: OSI Approved :: MIT License
Classifier: Operating System :: OS Independent
Requires-Python: >=3.9
License-File: LICENSE
Requires-Dist: aiohttp (>=3.8.1)
